OmerBinance/Apihelpers.py
OmerBinance/BinanceTrRequests.py
OmerBinance/BinanceTrService.py
OmerBinance/TimeModel.py
OmerBinance/UserModel.py
OmerBinance/__init__.py
OmerBinance/config.py
OmerBinance/constants.json
OmerBinance-2.0.dist-info/LICENSE
OmerBinance-2.0.dist-info/METADATA
OmerBinance-2.0.dist-info/WHEEL
OmerBinance-2.0.dist-info/top_level.txt
OmerBinance-2.0.dist-info/RECORD
